profile_metrics_local/__init__.py
profile_metrics_local/profile_metrics_local.py
profile_metrics_local-0.0.14.dist-info/METADATA
profile_metrics_local-0.0.14.dist-info/WHEEL
profile_metrics_local-0.0.14.dist-info/top_level.txt
profile_metrics_local-0.0.14.dist-info/RECORD
